{"place_id": "poland_2", "place_name": "Warsaw", "place_lat": "52.224729", "place_lon": "21.001417", "place_brief_desc": "Poland's capital and largest city, known for its Royal Castle, Palace of Culture and Science, and \u0141azienki Park.", "place_longer_desc": "Warsaw is a vibrant city with a lot to offer visitors. The Royal Castle is a must-see for anyone interested in Polish history. Visitors can also visit the Palace of Culture and Science, a towering Art Deco building, and \u0141azienki Park, a beautiful park with gardens, lakes, and palaces.", "place_image": "./static/images/warsaw.png", "place_tags": "history", "place_links": "./static/cards/warsaw.html", "place_country": "Poland", "hops": [{"place_id": "austria_1", "place_name": "Vienna", "place_lat": "48.207037", "place_lon": "16.341553", "duration_min": "555", "details": [{"agency_name": "FlixBus-eu", "route_short_name": "NULL", "route_long_name": "Warszawa - Katowice - Vienna", "agency_url": "https://global.flixbus.com", "duration_min": "555", "duration_avg": "629", "duration_count": "23"}]}, {"place_id": "belgium_1", "place_name": "Brussels", "place_lat": "50.835375", "place_lon": "4.335695", "duration_min": "1285", "details": [{"agency_name": "FlixBus-eu", "route_short_name": "NULL", "route_long_name": "Warsaw - Dresden - Brussels", "agency_url": "https://global.flixbus.com", "duration_min": "1285", "duration_avg": "1285", "duration_count": "19"}, {"agency_name": "FlixBus-de", "route_short_name": "NULL", "route_long_name": "Warsaw - Dresden - Brussels", "agency_url": "https://www.delfi.de", "duration_min": "1285", "duration_avg": "1285", "duration_count": "2"}]}, {"place_id": "belgium_3", "place_name": "Ghent", "place_lat": "51.035627", "place_lon": "3.710612", "duration_min": "1350", "details": [{"agency_name": "FlixBus-de", "route_short_name": "NULL", "route_long_name": "Bialystok - Amsterdam - Lille", "agency_url": "https://www.delfi.de", "duration_min": "1350", "duration_avg": "1350", "duration_count": "1"}, {"agency_name": "FlixBus-eu", "route_short_name": "NULL", "route_long_name": "Bialystok - Amsterdam - Lille", "agency_url": "https://global.flixbus.com", "duration_min": "1350", "duration_avg": "1350", "duration_count": "19"}]}, {"place_id": "belgium_4", "place_name": "Antwerp", "place_lat": "51.215807", "place_lon": "4.421165", "duration_min": "1280", "details": [{"agency_name": "FlixBus-eu", "route_short_name": "NULL", "route_long_name": "Bialystok - Amsterdam - Lille", "agency_url": "https://global.flixbus.com", "duration_min": "1280", "duration_avg": "1280", "duration_count": "16"}]}, {"place_id": "croatia_1", "place_name": "Zagreb", "place_lat": "45.807411", "place_lon": "15.990291", "duration_min": "935", "details": [{"agency_name": "FlixBus-eu", "route_short_name": "NULL", "route_long_name": "Warsaw - Krakow - Budapest/Zagreb", "agency_url": "https://global.flixbus.com", "duration_min": "1060", "duration_avg": "1060", "duration_count": "4"}, {"agency_name": "FlixBus-eu", "route_short_name": "NULL", "route_long_name": "Warsaw - Poprad - Budapest/Dubrovnik", "agency_url": "https://global.flixbus.com", "duration_min": "1079", "duration_avg": "1079", "duration_count": "4"}, {"agency_name": "FlixBus-eu", "route_short_name": "NULL", "route_long_name": "Warsaw - Zagreb/Baska", "agency_url": "https://global.flixbus.com", "duration_min": "935", "duration_avg": "935", "duration_count": "1"}]}, {"place_id": "croatia_2", "place_name": "Split", "place_lat": "43.504887", "place_lon": "16.44279", "duration_min": "1375", "details": [{"agency_name": "FlixBus-eu", "route_short_name": "NULL", "route_long_name": "Warsaw - Poprad - Budapest/Dubrovnik", "agency_url": "https://global.flixbus.com", "duration_min": "1375", "duration_avg": "1375", "duration_count": "4"}]}, {"place_id": "czechia_1", "place_name": "Prague", "place_lat": "50.081926", "place_lon": "14.451481", "duration_min": "520", "details": [{"agency_name": "FlixBus-eu", "route_short_name": "NULL", "route_long_name": "Bialystok - Warsaw - Prague", "agency_url": "https://global.flixbus.com", "duration_min": "575", "duration_avg": "575", "duration_count": "8"}, {"agency_name": "FlixBus-eu", "route_short_name": "NULL", "route_long_name": "Tallinn - Warsaw - Prague", "agency_url": "https://global.flixbus.com", "duration_min": "665", "duration_avg": "665", "duration_count": "4"}, {"agency_name": "FlixBus-eu", "route_short_name": "NULL", "route_long_name": "Warsaw - Jelenia Gora - Prague", "agency_url": "https://global.flixbus.com", "duration_min": "560", "duration_avg": "560", "duration_count": "19"}, {"agency_name": "FlixBus-eu", "route_short_name": "NULL", "route_long_name": "Warsaw - Kudowa Zdroj - Prague", "agency_url": "https://global.flixbus.com", "duration_min": "625", "duration_avg": "625", "duration_count": "19"}, {"agency_name": "FlixBus-eu", "route_short_name": "NULL", "route_long_name": "Warsaw - Liberec - Prague", "agency_url": "https://global.flixbus.com", "duration_min": "600", "duration_avg": "600", "duration_count": "19"}, {"agency_name": "FlixBus-eu", "route_short_name": "NULL", "route_long_name": "Warsaw - Prague", "agency_url": "https://global.flixbus.com", "duration_min": "520", "duration_avg": "520", "duration_count": "3"}, {"agency_name": "FlixBus-eu", "route_short_name": "NULL", "route_long_name": "Wegorzewo/ Olsztyn - Warsaw - Prague", "agency_url": "https://global.flixbus.com", "duration_min": "650", "duration_avg": "650", "duration_count": "21"}, {"agency_name": "Flixbus Polska sp.o.o", "route_short_name": "NULL", "route_long_name": "Praha - Tallinn", "agency_url": "https://www.flixbus.ee/", "duration_min": "665", "duration_avg": "665", "duration_count": "1"}]}, {"place_id": "czechia_5", "place_name": "Brno", "place_lat": "49.190537", "place_lon": "16.612776", "duration_min": "435", "details": [{"agency_name": "Flixbus Polska sp.o.o", "route_short_name": "NULL", "route_long_name": "Praha - Tallinn", "agency_url": "https://www.flixbus.ee/", "duration_min": "495", "duration_avg": "495", "duration_count": "1"}, {"agency_name": "FlixBus-eu", "route_short_name": "NULL", "route_long_name": "Tallinn - Warsaw - Prague", "agency_url": "https://global.flixbus.com", "duration_min": "495", "duration_avg": "495", "duration_count": "4"}, {"agency_name": "FlixBus-eu", "route_short_name": "NULL", "route_long_name": "Warsaw - Zagreb/Baska", "agency_url": "https://global.flixbus.com", "duration_min": "435", "duration_avg": "435", "duration_count": "4"}, {"agency_name": "FlixBus-eu", "route_short_name": "NULL", "route_long_name": "Warszawa - Katowice - Vienna", "agency_url": "https://global.flixbus.com", "duration_min": "435", "duration_avg": "496", "duration_count": "23"}]}, {"place_id": "czechia_7", "place_name": "Olomouc", "place_lat": "49.593128", "place_lon": "17.277932", "duration_min": "370", "details": [{"agency_name": "FlixBus-eu", "route_short_name": "NULL", "route_long_name": "Tallinn - Warsaw - Prague", "agency_url": "https://global.flixbus.com", "duration_min": "420", "duration_avg": "420", "duration_count": "4"}, {"agency_name": "FlixBus-eu", "route_short_name": "NULL", "route_long_name": "Warszawa - Katowice - Vienna", "agency_url": "https://global.flixbus.com", "duration_min": "370", "duration_avg": "427", "duration_count": "23"}, {"agency_name": "Flixbus Polska sp.o.o", "route_short_name": "NULL", "route_long_name": "Praha - Tallinn", "agency_url": "https://www.flixbus.ee/", "duration_min": "420", "duration_avg": "420", "duration_count": "1"}]}, {"place_id": "czechia_9", "place_name": "Liberec", "place_lat": "50.761429", "place_lon": "15.045947", "duration_min": "460", "details": [{"agency_name": "FlixBus-eu", "route_short_name": "NULL", "route_long_name": "Warsaw - Jelenia Gora - Prague", "agency_url": "https://global.flixbus.com", "duration_min": "460", "duration_avg": "460", "duration_count": "19"}, {"agency_name": "FlixBus-eu", "route_short_name": "NULL", "route_long_name": "Warsaw - Liberec - Prague", "agency_url": "https://global.flixbus.com", "duration_min": "495", "duration_avg": "495", "duration_count": "19"}]}, {"place_id": "estonia_1", "place_name": "Tallinn", "place_lat": "59.437296", "place_lon": "24.744777", "duration_min": "875", "details": [{"agency_name": "FlixBus-eu", "route_short_name": "NULL", "route_long_name": "Tallinn - Warsaw - Berlin", "agency_url": "https://global.flixbus.com", "duration_min": "875", "duration_avg": "875", "duration_count": "4"}, {"agency_name": "FlixBus-eu", "route_short_name": "NULL", "route_long_name": "Tallinn - Warsaw - Prague", "agency_url": "https://global.flixbus.com", "duration_min": "1060", "duration_avg": "1060", "duration_count": "4"}, {"agency_name": "FlixBus-eu", "route_short_name": "NULL", "route_long_name": "Vaasa - Helsinki - Warsaw", "agency_url": "https://global.flixbus.com", "duration_min": "935", "duration_avg": "945", "duration_count": "8"}, {"agency_name": "FlixBus-de", "route_short_name": "NULL", "route_long_name": "Tallinn - Warsaw - Berlin", "agency_url": "https://www.delfi.de", "duration_min": "875", "duration_avg": "875", "duration_count": "1"}, {"agency_name": "Flixbus Polska sp.o.o", "route_short_name": "NULL", "route_long_name": "Praha - Tallinn", "agency_url": "https://www.flixbus.ee/", "duration_min": "1100", "duration_avg": "1100", "duration_count": "1"}]}, {"place_id": "finland_1", "place_name": "Helsinki", "place_lat": "60.171742", "place_lon": "24.941443", "duration_min": "1165", "details": [{"agency_name": "FlixBus-eu", "route_short_name": "NULL", "route_long_name": "Vaasa - Helsinki - Warsaw", "agency_url": "https://global.flixbus.com", "duration_min": "1165", "duration_avg": "1185", "duration_count": "8"}]}, {"place_id": "finland_3", "place_name": "Turku", "place_lat": "60.454012", "place_lon": "22.252833", "duration_min": "1345", "details": [{"agency_name": "FlixBus-eu", "route_short_name": "NULL", "route_long_name": "Vaasa - Helsinki - Warsaw", "agency_url": "https://global.flixbus.com", "duration_min": "1345", "duration_avg": "1345", "duration_count": "4"}]}, {"place_id": "finland_5", "place_name": "Vaasa", "place_lat": "63.097578", "place_lon": "21.621736", "duration_min": "1655", "details": [{"agency_name": "FlixBus-eu", "route_short_name": "NULL", "route_long_name": "Vaasa - Helsinki - Warsaw", "agency_url": "https://global.flixbus.com", "duration_min": "1655", "duration_avg": "1655", "duration_count": "4"}]}, {"place_id": "france_155", "place_name": "Lille", "place_lat": "50.64501", "place_lon": "3.082257", "duration_min": "1415", "details": [{"agency_name": "FlixBus-eu", "route_short_name": "NULL", "route_long_name": "Bialystok - Amsterdam - Lille", "agency_url": "https://global.flixbus.com", "duration_min": "1415", "duration_avg": "1415", "duration_count": "19"}, {"agency_name": "FlixBus-de", "route_short_name": "NULL", "route_long_name": "Bialystok - Amsterdam - Lille", "agency_url": "https://www.delfi.de", "duration_min": "1415", "duration_avg": "1415", "duration_count": "1"}]}, {"place_id": "france_162", "place_name": "Strasbourg", "place_lat": "48.585339", "place_lon": "7.734067", "duration_min": "1110", "details": [{"agency_name": "FlixBus-de", "route_short_name": "NULL", "route_long_name": "Warsaw - Berlin - Lyon", "agency_url": "https://www.delfi.de", "duration_min": "1110", "duration_avg": "1110", "duration_count": "1"}, {"agency_name": "FlixBus-eu", "route_short_name": "NULL", "route_long_name": "Warsaw - Berlin - Lyon", "agency_url": "https://global.flixbus.com", "duration_min": "1110", "duration_avg": "1110", "duration_count": "19"}]}, {"place_id": "france_19", "place_name": "Paris", "place_lat": "48.8404960", "place_lon": "2.36707900", "duration_min": "1400", "details": [{"agency_name": "FlixBus-eu", "route_short_name": "NULL", "route_long_name": "Warsaw - Berlin - Paris", "agency_url": "https://global.flixbus.com", "duration_min": "1475", "duration_avg": "1475", "duration_count": "8"}, {"agency_name": "FlixBus-eu", "route_short_name": "NULL", "route_long_name": "Warsaw - Frankfurt - Paris", "agency_url": "https://global.flixbus.com", "duration_min": "1400", "duration_avg": "1400", "duration_count": "19"}, {"agency_name": "FlixBus-de", "route_short_name": "NULL", "route_long_name": "Warsaw - Berlin - Paris", "agency_url": "https://www.delfi.de", "duration_min": "1475", "duration_avg": "1475", "duration_count": "1"}, {"agency_name": "FlixBus-de", "route_short_name": "NULL", "route_long_name": "Warsaw - Frankfurt - Paris", "agency_url": "https://www.delfi.de", "duration_min": "1400", "duration_avg": "1400", "duration_count": "2"}]}, {"place_id": "france_93", "place_name": "Lyon", "place_lat": "45.7605960", "place_lon": "4.85940900", "duration_min": "1560", "details": [{"agency_name": "FlixBus-de", "route_short_name": "NULL", "route_long_name": "Warsaw - Berlin - Lyon", "agency_url": "https://www.delfi.de", "duration_min": "1560", "duration_avg": "1560", "duration_count": "1"}, {"agency_name": "FlixBus-eu", "route_short_name": "NULL", "route_long_name": "Warsaw - Berlin - Lyon", "agency_url": "https://global.flixbus.com", "duration_min": "1560", "duration_avg": "1560", "duration_count": "19"}]}, {"place_id": "Germany_2", "place_name": "Dresden", "place_lat": "51.040221", "place_lon": "13.731409", "duration_min": "495", "details": [{"agency_name": "FlixBus-eu", "route_short_name": "NULL", "route_long_name": "Modlin \u00d4\u00c7\u00f4 Wroclaw \u00d4\u00c7\u00f4 Ulm", "agency_url": "https://global.flixbus.com", "duration_min": "570", "duration_avg": "570", "duration_count": "8"}, {"agency_name": "FlixBus-eu", "route_short_name": "NULL", "route_long_name": "Warsaw - Dresden - Brussels", "agency_url": "https://global.flixbus.com", "duration_min": "545", "duration_avg": "545", "duration_count": "19"}, {"agency_name": "FlixBus-eu", "route_short_name": "NULL", "route_long_name": "Warsaw - Frankfurt - Paris", "agency_url": "https://global.flixbus.com", "duration_min": "535", "duration_avg": "535", "duration_count": "19"}, {"agency_name": "FlixBus-eu", "route_short_name": "NULL", "route_long_name": "Warsaw - Munich - Salzburg", "agency_url": "https://global.flixbus.com", "duration_min": "495", "duration_avg": "495", "duration_count": "19"}, {"agency_name": "FlixBus-eu", "route_short_name": "NULL", "route_long_name": "Warsaw - Munich - Zurich", "agency_url": "https://global.flixbus.com", "duration_min": "505", "duration_avg": "505", "duration_count": "35"}, {"agency_name": "FlixBus-de", "route_short_name": "NULL", "route_long_name": "Modlin \u00d4\u00c7\u00f4 Wroclaw \u00d4\u00c7\u00f4 Ulm", "agency_url": "https://www.delfi.de", "duration_min": "570", "duration_avg": "570", "duration_count": "2"}, {"agency_name": "FlixBus-de", "route_short_name": "NULL", "route_long_name": "Warsaw - Dresden - Brussels", "agency_url": "https://www.delfi.de", "duration_min": "545", "duration_avg": "545", "duration_count": "2"}, {"agency_name": "FlixBus-de", "route_short_name": "NULL", "route_long_name": "Warsaw - Frankfurt - Paris", "agency_url": "https://www.delfi.de", "duration_min": "535", "duration_avg": "535", "duration_count": "2"}, {"agency_name": "FlixBus-de", "route_short_name": "NULL", "route_long_name": "Warsaw - Munich - Salzburg", "agency_url": "https://www.delfi.de", "duration_min": "495", "duration_avg": "495", "duration_count": "2"}, {"agency_name": "FlixBus-de", "route_short_name": "NULL", "route_long_name": "Warsaw - Munich - Zurich", "agency_url": "https://www.delfi.de", "duration_min": "505", "duration_avg": "505", "duration_count": "4"}]}, {"place_id": "Germany_3", "place_name": "Nuremberg", "place_lat": "49.450748", "place_lon": "11.077955", "duration_min": "760", "details": [{"agency_name": "FlixBus-de", "route_short_name": "NULL", "route_long_name": "Warsaw - Munich - Zurich", "agency_url": "https://www.delfi.de", "duration_min": "760", "duration_avg": "760", "duration_count": "4"}, {"agency_name": "FlixBus-eu", "route_short_name": "NULL", "route_long_name": "Warsaw - Munich - Zurich", "agency_url": "https://global.flixbus.com", "duration_min": "760", "duration_avg": "760", "duration_count": "35"}]}, {"place_id": "Germany_4", "place_name": "Munich", "place_lat": "48.140364", "place_lon": "11.558744", "duration_min": "910", "details": [{"agency_name": "FlixBus-eu", "route_short_name": "NULL", "route_long_name": "Warsaw - Munich - Salzburg", "agency_url": "https://global.flixbus.com", "duration_min": "925", "duration_avg": "925", "duration_count": "19"}, {"agency_name": "FlixBus-eu", "route_short_name": "NULL", "route_long_name": "Warsaw - Munich - Zurich", "agency_url": "https://global.flixbus.com", "duration_min": "910", "duration_avg": "910", "duration_count": "35"}, {"agency_name": "FlixBus-de", "route_short_name": "NULL", "route_long_name": "Warsaw - Munich - Salzburg", "agency_url": "https://www.delfi.de", "duration_min": "925", "duration_avg": "925", "duration_count": "2"}, {"agency_name": "FlixBus-de", "route_short_name": "NULL", "route_long_name": "Warsaw - Munich - Zurich", "agency_url": "https://www.delfi.de", "duration_min": "910", "duration_avg": "910", "duration_count": "4"}]}, {"place_id": "Germany_7", "place_name": "Hamburg", "place_lat": "53.55711", "place_lon": "9.997434", "duration_min": "670", "details": [{"agency_name": "FlixBus-de", "route_short_name": "NULL", "route_long_name": "Warsaw - Berlin - Flensburg", "agency_url": "https://www.delfi.de", "duration_min": "670", "duration_avg": "670", "duration_count": "1"}, {"agency_name": "FlixBus-de", "route_short_name": "NULL", "route_long_name": "Warsaw - Berlin - Hamburg", "agency_url": "https://www.delfi.de", "duration_min": "720", "duration_avg": "720", "duration_count": "1"}, {"agency_name": "FlixBus-eu", "route_short_name": "NULL", "route_long_name": "Warsaw - Berlin - Flensburg", "agency_url": "https://global.flixbus.com", "duration_min": "670", "duration_avg": "670", "duration_count": "8"}, {"agency_name": "FlixBus-eu", "route_short_name": "NULL", "route_long_name": "Warsaw - Berlin - Hamburg", "agency_url": "https://global.flixbus.com", "duration_min": "720", "duration_avg": "720", "duration_count": "19"}]}, {"place_id": "hungary_1", "place_name": "Budapest", "place_lat": "47.519551", "place_lon": "19.054084", "duration_min": "675", "details": [{"agency_name": "FlixBus-eu", "route_short_name": "NULL", "route_long_name": "Warszawa - Krak\u251c\u2502w - Budapest", "agency_url": "https://global.flixbus.com", "duration_min": "675", "duration_avg": "675", "duration_count": "19"}]}, {"place_id": "hungary_5", "place_name": "Debrecen", "place_lat": "47.519631", "place_lon": "21.628792", "duration_min": "925", "details": [{"agency_name": "FlixBus-eu", "route_short_name": "NULL", "route_long_name": "Warsaw - Budapest -  Bucharest", "agency_url": "https://global.flixbus.com", "duration_min": "925", "duration_avg": "925", "duration_count": "6"}]}, {"place_id": "hungary_7", "place_name": "Gyor", "place_lat": "47.681986", "place_lon": "17.634795", "duration_min": "600", "details": [{"agency_name": "FlixBus-eu", "route_short_name": "NULL", "route_long_name": "Warsaw - Budapest -  Bucharest", "agency_url": "https://global.flixbus.com", "duration_min": "600", "duration_avg": "600", "duration_count": "9"}]}, {"place_id": "lithuania_1", "place_name": "Vilnius", "place_lat": "54.670236", "place_lon": "25.282908", "duration_min": "410", "details": [{"agency_name": "FlixBus-eu", "route_short_name": "NULL", "route_long_name": "Riga - Vilnius - Warsaw", "agency_url": "https://global.flixbus.com", "duration_min": "459", "duration_avg": "473", "duration_count": "57"}, {"agency_name": "FlixBus-eu", "route_short_name": "NULL", "route_long_name": "Tallinn - Warsaw - Prague", "agency_url": "https://global.flixbus.com", "duration_min": "500", "duration_avg": "517", "duration_count": "12"}, {"agency_name": "FlixBus-eu", "route_short_name": "NULL", "route_long_name": "Vilnius - Warsaw", "agency_url": "https://global.flixbus.com", "duration_min": "410", "duration_avg": "419", "duration_count": "46"}, {"agency_name": "FlixBus-eu", "route_short_name": "NULL", "route_long_name": "Vilnius - Warsaw - Berlin", "agency_url": "https://global.flixbus.com", "duration_min": "510", "duration_avg": "517", "duration_count": "8"}, {"agency_name": "FlixBus-de", "route_short_name": "NULL", "route_long_name": "Vilnius - Warsaw - Berlin", "agency_url": "https://www.delfi.de", "duration_min": "510", "duration_avg": "517", "duration_count": "2"}, {"agency_name": "Flixbus Polska sp.o.o", "route_short_name": "NULL", "route_long_name": "Praha - Tallinn", "agency_url": "https://www.flixbus.ee/", "duration_min": "540", "duration_avg": "557", "duration_count": "3"}]}, {"place_id": "lithuania_2", "place_name": "Kaunas", "place_lat": "54.886291", "place_lon": "23.931766", "duration_min": "335", "details": [{"agency_name": "FlixBus-de", "route_short_name": "NULL", "route_long_name": "Tallinn - Warsaw - Berlin", "agency_url": "https://www.delfi.de", "duration_min": "350", "duration_avg": "350", "duration_count": "1"}, {"agency_name": "FlixBus-de", "route_short_name": "NULL", "route_long_name": "Vilnius - Warsaw - Berlin", "agency_url": "https://www.delfi.de", "duration_min": "420", "duration_avg": "420", "duration_count": "1"}, {"agency_name": "FlixBus-eu", "route_short_name": "NULL", "route_long_name": "Riga - Kaunas - Warsaw", "agency_url": "https://global.flixbus.com", "duration_min": "335", "duration_avg": "335", "duration_count": "4"}, {"agency_name": "FlixBus-eu", "route_short_name": "NULL", "route_long_name": "Riga - Warsaw - Vienna", "agency_url": "https://global.flixbus.com", "duration_min": "435", "duration_avg": "435", "duration_count": "4"}, {"agency_name": "FlixBus-eu", "route_short_name": "NULL", "route_long_name": "Tallinn - Warsaw - Berlin", "agency_url": "https://global.flixbus.com", "duration_min": "350", "duration_avg": "350", "duration_count": "4"}, {"agency_name": "FlixBus-eu", "route_short_name": "NULL", "route_long_name": "Vaasa - Helsinki - Warsaw", "agency_url": "https://global.flixbus.com", "duration_min": "340", "duration_avg": "340", "duration_count": "4"}, {"agency_name": "FlixBus-eu", "route_short_name": "NULL", "route_long_name": "Vilnius - Warsaw - Berlin", "agency_url": "https://global.flixbus.com", "duration_min": "420", "duration_avg": "420", "duration_count": "4"}]}, {"place_id": "netherlands_2", "place_name": "Rotterdam", "place_lat": "51.924804", "place_lon": "4.468771", "duration_min": "1165", "details": [{"agency_name": "FlixBus-eu", "route_short_name": "NULL", "route_long_name": "Bialystok - Amsterdam - Lille", "agency_url": "https://global.flixbus.com", "duration_min": "1165", "duration_avg": "1165", "duration_count": "19"}, {"agency_name": "FlixBus-de", "route_short_name": "NULL", "route_long_name": "Bialystok - Amsterdam - Lille", "agency_url": "https://www.delfi.de", "duration_min": "1165", "duration_avg": "1165", "duration_count": "1"}]}, {"place_id": "netherlands_3", "place_name": "Utrecht", "place_lat": "52.089397", "place_lon": "5.109864", "duration_min": "1120", "details": [{"agency_name": "FlixBus-de", "route_short_name": "NULL", "route_long_name": "Warsaw - Berlin - Amsterdam", "agency_url": "https://www.delfi.de", "duration_min": "1120", "duration_avg": "1120", "duration_count": "1"}, {"agency_name": "FlixBus-eu", "route_short_name": "NULL", "route_long_name": "Warsaw - Berlin - Amsterdam", "agency_url": "https://global.flixbus.com", "duration_min": "1120", "duration_avg": "1120", "duration_count": "8"}]}, {"place_id": "netherlands_4", "place_name": "Den Haag", "place_lat": "52.080408", "place_lon": "4.325169", "duration_min": "1130", "details": [{"agency_name": "FlixBus-eu", "route_short_name": "NULL", "route_long_name": "Bialystok - Amsterdam - Lille", "agency_url": "https://global.flixbus.com", "duration_min": "1130", "duration_avg": "1130", "duration_count": "19"}, {"agency_name": "FlixBus-de", "route_short_name": "NULL", "route_long_name": "Bialystok - Amsterdam - Lille", "agency_url": "https://www.delfi.de", "duration_min": "1130", "duration_avg": "1130", "duration_count": "1"}]}, {"place_id": "netherlands_8", "place_name": "Maastricht", "place_lat": "50.849811", "place_lon": "5.705876", "duration_min": "1175", "details": [{"agency_name": "FlixBus-de", "route_short_name": "NULL", "route_long_name": "Warsaw - Dresden - Brussels", "agency_url": "https://www.delfi.de", "duration_min": "1175", "duration_avg": "1175", "duration_count": "2"}, {"agency_name": "FlixBus-eu", "route_short_name": "NULL", "route_long_name": "Warsaw - Dresden - Brussels", "agency_url": "https://global.flixbus.com", "duration_min": "1175", "duration_avg": "1175", "duration_count": "19"}]}, {"place_id": "poland_1", "place_name": "Krakow", "place_lat": "50.069934", "place_lon": "19.940546", "duration_min": "235", "details": [{"agency_name": "FlixBus-eu", "route_short_name": "NULL", "route_long_name": "Olsztyn - Warsaw - Zakopane", "agency_url": "https://global.flixbus.com", "duration_min": "270", "duration_avg": "270", "duration_count": "19"}, {"agency_name": "FlixBus-eu", "route_short_name": "NULL", "route_long_name": "Riga - Warsaw - Vienna", "agency_url": "https://global.flixbus.com", "duration_min": "265", "duration_avg": "265", "duration_count": "4"}, {"agency_name": "FlixBus-eu", "route_short_name": "NULL", "route_long_name": "Warsaw - Krak\u251c\u2502w", "agency_url": "https://global.flixbus.com", "duration_min": "235", "duration_avg": "251", "duration_count": "16"}, {"agency_name": "FlixBus-eu", "route_short_name": "NULL", "route_long_name": "Warsaw - Krak\u251c\u2502w - Zakopane", "agency_url": "https://global.flixbus.com", "duration_min": "276", "duration_avg": "276", "duration_count": "19"}, {"agency_name": "FlixBus-eu", "route_short_name": "NULL", "route_long_name": "Warsaw - Krakow - Budapest/Zagreb", "agency_url": "https://global.flixbus.com", "duration_min": "245", "duration_avg": "245", "duration_count": "20"}, {"agency_name": "FlixBus-eu", "route_short_name": "NULL", "route_long_name": "Warsaw - Poprad - Budapest/Dubrovnik", "agency_url": "https://global.flixbus.com", "duration_min": "255", "duration_avg": "255", "duration_count": "26"}, {"agency_name": "FlixBus-eu", "route_short_name": "NULL", "route_long_name": "Warszawa - Krak\u251c\u2502w - Budapest", "agency_url": "https://global.flixbus.com", "duration_min": "245", "duration_avg": "245", "duration_count": "19"}, {"agency_name": "FlixBus-eu", "route_short_name": "NULL", "route_long_name": "Warszawa - Krak\u251c\u2502w - Kosice", "agency_url": "https://global.flixbus.com", "duration_min": "265", "duration_avg": "265", "duration_count": "39"}, {"agency_name": "FlixBus-eu", "route_short_name": "NULL", "route_long_name": "Warszawa - Krak\u251c\u2502w - Zakopane", "agency_url": "https://global.flixbus.com", "duration_min": "265", "duration_avg": "268", "duration_count": "57"}]}, {"place_id": "poland_3", "place_name": "Wroclaw", "place_lat": "51.098075", "place_lon": "17.037084", "duration_min": "235", "details": [{"agency_name": "FlixBus-eu", "route_short_name": "NULL", "route_long_name": "Bialystok - Warsaw - Prague", "agency_url": "https://global.flixbus.com", "duration_min": "295", "duration_avg": "305", "duration_count": "16"}, {"agency_name": "FlixBus-eu", "route_short_name": "NULL", "route_long_name": "Modlin - Warsaw - Wroc\u253c\u00e9aw", "agency_url": "https://global.flixbus.com", "duration_min": "275", "duration_avg": "282", "duration_count": "38"}, {"agency_name": "FlixBus-eu", "route_short_name": "NULL", "route_long_name": "Modlin \u00d4\u00c7\u00f4 Wroclaw \u00d4\u00c7\u00f4 Ulm", "agency_url": "https://global.flixbus.com", "duration_min": "310", "duration_avg": "317", "duration_count": "16"}, {"agency_name": "FlixBus-eu", "route_short_name": "NULL", "route_long_name": "Warsaw - Dresden - Brussels", "agency_url": "https://global.flixbus.com", "duration_min": "260", "duration_avg": "270", "duration_count": "38"}, {"agency_name": "FlixBus-eu", "route_short_name": "NULL", "route_long_name": "Warsaw - Frankfurt - Paris", "agency_url": "https://global.flixbus.com", "duration_min": "285", "duration_avg": "295", "duration_count": "38"}, {"agency_name": "FlixBus-eu", "route_short_name": "NULL", "route_long_name": "Warsaw - Jelenia Gora - Prague", "agency_url": "https://global.flixbus.com", "duration_min": "245", "duration_avg": "255", "duration_count": "38"}, {"agency_name": "FlixBus-eu", "route_short_name": "NULL", "route_long_name": "Warsaw - Kudowa Zdroj - Prague", "agency_url": "https://global.flixbus.com", "duration_min": "295", "duration_avg": "305", "duration_count": "38"}, {"agency_name": "FlixBus-eu", "route_short_name": "NULL", "route_long_name": "Warsaw - Liberec - Prague", "agency_url": "https://global.flixbus.com", "duration_min": "295", "duration_avg": "302", "duration_count": "38"}, {"agency_name": "FlixBus-eu", "route_short_name": "NULL", "route_long_name": "Warsaw - Munich - Salzburg", "agency_url": "https://global.flixbus.com", "duration_min": "235", "duration_avg": "245", "duration_count": "38"}, {"agency_name": "FlixBus-eu", "route_short_name": "NULL", "route_long_name": "Warsaw - Munich - Zurich", "agency_url": "https://global.flixbus.com", "duration_min": "245", "duration_avg": "255", "duration_count": "70"}, {"agency_name": "FlixBus-eu", "route_short_name": "NULL", "route_long_name": "Warsaw - Prague", "agency_url": "https://global.flixbus.com", "duration_min": "245", "duration_avg": "262", "duration_count": "14"}, {"agency_name": "FlixBus-eu", "route_short_name": "NULL", "route_long_name": "Warsaw - Wroc\u253c\u00e9aw - Karpacz", "agency_url": "https://global.flixbus.com", "duration_min": "240", "duration_avg": "275", "duration_count": "76"}, {"agency_name": "FlixBus-eu", "route_short_name": "NULL", "route_long_name": "Wegorzewo/ Olsztyn - Warsaw - Prague", "agency_url": "https://global.flixbus.com", "duration_min": "290", "duration_avg": "297", "duration_count": "42"}, {"agency_name": "FlixBus-de", "route_short_name": "NULL", "route_long_name": "Modlin \u00d4\u00c7\u00f4 Wroclaw \u00d4\u00c7\u00f4 Ulm", "agency_url": "https://www.delfi.de", "duration_min": "310", "duration_avg": "317", "duration_count": "4"}, {"agency_name": "FlixBus-de", "route_short_name": "NULL", "route_long_name": "Warsaw - Dresden - Brussels", "agency_url": "https://www.delfi.de", "duration_min": "260", "duration_avg": "270", "duration_count": "4"}, {"agency_name": "FlixBus-de", "route_short_name": "NULL", "route_long_name": "Warsaw - Frankfurt - Paris", "agency_url": "https://www.delfi.de", "duration_min": "285", "duration_avg": "295", "duration_count": "4"}, {"agency_name": "FlixBus-de", "route_short_name": "NULL", "route_long_name": "Warsaw - Munich - Salzburg", "agency_url": "https://www.delfi.de", "duration_min": "235", "duration_avg": "245", "duration_count": "4"}, {"agency_name": "FlixBus-de", "route_short_name": "NULL", "route_long_name": "Warsaw - Munich - Zurich", "agency_url": "https://www.delfi.de", "duration_min": "245", "duration_avg": "255", "duration_count": "8"}]}, {"place_id": "poland_4", "place_name": "Gdansk", "place_lat": "54.365843", "place_lon": "18.64396", "duration_min": "305", "details": [{"agency_name": "FlixBus-eu", "route_short_name": "NULL", "route_long_name": "\u253c\u00fceba/Gda\u253c\u00e4sk - Warsaw", "agency_url": "https://global.flixbus.com", "duration_min": "366", "duration_avg": "366", "duration_count": "20"}, {"agency_name": "FlixBus-eu", "route_short_name": "NULL", "route_long_name": "\u253c\u00fceba/Gdynia/Karwia - Warsaw", "agency_url": "https://global.flixbus.com", "duration_min": "305", "duration_avg": "311", "duration_count": "74"}, {"agency_name": "FlixBus-eu", "route_short_name": "NULL", "route_long_name": "Gda\u253c\u00e4sk Airport - Przemy\u253c\u00f8l /Ustrzyki G\u251c\u2502rne", "agency_url": "https://global.flixbus.com", "duration_min": "410", "duration_avg": "410", "duration_count": "14"}, {"agency_name": "FlixBus-eu", "route_short_name": "NULL", "route_long_name": "Kyiv - Torun - Gdynia", "agency_url": "https://global.flixbus.com", "duration_min": "375", "duration_avg": "375", "duration_count": "3"}, {"agency_name": "FlixBus-eu", "route_short_name": "NULL", "route_long_name": "Ustka - Gdansk - Warsaw", "agency_url": "https://global.flixbus.com", "duration_min": "340", "duration_avg": "340", "duration_count": "4"}]}, {"place_id": "poland_6", "place_name": "Poznan", "place_lat": "52.410249", "place_lon": "16.905366", "duration_min": "205", "details": [{"agency_name": "FlixBus-eu", "route_short_name": "NULL", "route_long_name": "Bialystok - Amsterdam - Lille", "agency_url": "https://global.flixbus.com", "duration_min": "215", "duration_avg": "215", "duration_count": "19"}, {"agency_name": "FlixBus-eu", "route_short_name": "NULL", "route_long_name": "Hrubiesz\u251c\u2502w - Warszaw - Bonn", "agency_url": "https://global.flixbus.com", "duration_min": "215", "duration_avg": "237", "duration_count": "8"}, {"agency_name": "FlixBus-eu", "route_short_name": "NULL", "route_long_name": "Kyiv - Warszawa - Poznan", "agency_url": "https://global.flixbus.com", "duration_min": "275", "duration_avg": "275", "duration_count": "4"}, {"agency_name": "FlixBus-eu", "route_short_name": "NULL", "route_long_name": "Vilnius - Warsaw - Berlin", "agency_url": "https://global.flixbus.com", "duration_min": "220", "duration_avg": "220", "duration_count": "4"}, {"agency_name": "FlixBus-eu", "route_short_name": "NULL", "route_long_name": "Warsaw - Berlin - Amsterdam", "agency_url": "https://global.flixbus.com", "duration_min": "270", "duration_avg": "270", "duration_count": "8"}, {"agency_name": "FlixBus-eu", "route_short_name": "NULL", "route_long_name": "Warsaw - Berlin - Flensburg", "agency_url": "https://global.flixbus.com", "duration_min": "215", "duration_avg": "215", "duration_count": "8"}, {"agency_name": "FlixBus-eu", "route_short_name": "NULL", "route_long_name": "Warsaw - Berlin - Lyon", "agency_url": "https://global.flixbus.com", "duration_min": "215", "duration_avg": "215", "duration_count": "19"}, {"agency_name": "FlixBus-eu", "route_short_name": "NULL", "route_long_name": "Warsaw - Berlin - Paris", "agency_url": "https://global.flixbus.com", "duration_min": "245", "duration_avg": "245", "duration_count": "8"}, {"agency_name": "FlixBus-eu", "route_short_name": "NULL", "route_long_name": "Warsaw - Pozna\u253c\u00e4 - Szczecin", "agency_url": "https://global.flixbus.com", "duration_min": "265", "duration_avg": "265", "duration_count": "19"}, {"agency_name": "FlixBus-eu", "route_short_name": "NULL", "route_long_name": "Warsaw - Pozna\u253c\u00e4/Zielona G\u251c\u2502ra", "agency_url": "https://global.flixbus.com", "duration_min": "205", "duration_avg": "205", "duration_count": "32"}, {"agency_name": "FlixBus-de", "route_short_name": "NULL", "route_long_name": "Bialystok - Amsterdam - Lille", "agency_url": "https://www.delfi.de", "duration_min": "215", "duration_avg": "215", "duration_count": "1"}, {"agency_name": "FlixBus-de", "route_short_name": "NULL", "route_long_name": "Hrubiesz\u251c\u2502w - Warszaw - Bonn", "agency_url": "https://www.delfi.de", "duration_min": "215", "duration_avg": "237", "duration_count": "2"}, {"agency_name": "FlixBus-de", "route_short_name": "NULL", "route_long_name": "Vilnius - Warsaw - Berlin", "agency_url": "https://www.delfi.de", "duration_min": "220", "duration_avg": "220", "duration_count": "1"}, {"agency_name": "FlixBus-de", "route_short_name": "NULL", "route_long_name": "Warsaw - Berlin - Amsterdam", "agency_url": "https://www.delfi.de", "duration_min": "270", "duration_avg": "270", "duration_count": "1"}, {"agency_name": "FlixBus-de", "route_short_name": "NULL", "route_long_name": "Warsaw - Berlin - Flensburg", "agency_url": "https://www.delfi.de", "duration_min": "215", "duration_avg": "215", "duration_count": "1"}, {"agency_name": "FlixBus-de", "route_short_name": "NULL", "route_long_name": "Warsaw - Berlin - Lyon", "agency_url": "https://www.delfi.de", "duration_min": "215", "duration_avg": "215", "duration_count": "1"}, {"agency_name": "FlixBus-de", "route_short_name": "NULL", "route_long_name": "Warsaw - Berlin - Paris", "agency_url": "https://www.delfi.de", "duration_min": "245", "duration_avg": "245", "duration_count": "1"}]}, {"place_id": "poland_7", "place_name": "Bielsko-Biala", "place_lat": "49.830713", "place_lon": "19.04558", "duration_min": "385", "details": [{"agency_name": "FlixBus-eu", "route_short_name": "NULL", "route_long_name": "Riga - Warsaw - Vienna", "agency_url": "https://global.flixbus.com", "duration_min": "385", "duration_avg": "385", "duration_count": "4"}]}, {"place_id": "romania_2", "place_name": "Brasov", "place_lat": "46.226398", "place_lon": "24.795737", "duration_min": "1345", "details": [{"agency_name": "FlixBus-eu", "route_short_name": "NULL", "route_long_name": "Warsaw - Budapest -  Bucharest", "agency_url": "https://global.flixbus.com", "duration_min": "1345", "duration_avg": "1345", "duration_count": "5"}]}, {"place_id": "romania_4", "place_name": "Targu Mures", "place_lat": "46.533344", "place_lon": "24.549316", "duration_min": "1280", "details": [{"agency_name": "FlixBus-eu", "route_short_name": "NULL", "route_long_name": "Warsaw - Budapest -  Bucharest", "agency_url": "https://global.flixbus.com", "duration_min": "1280", "duration_avg": "1280", "duration_count": "5"}]}, {"place_id": "romania_6", "place_name": "Cluj-Napoca", "place_lat": "46.784197", "place_lon": "23.586616", "duration_min": "1190", "details": [{"agency_name": "FlixBus-eu", "route_short_name": "NULL", "route_long_name": "Warsaw - Budapest -  Bucharest", "agency_url": "https://global.flixbus.com", "duration_min": "1190", "duration_avg": "1190", "duration_count": "6"}]}, {"place_id": "slovakia_1", "place_name": "Bratislava", "place_lat": "48.154135", "place_lon": "17.097852", "duration_min": "535", "details": [{"agency_name": "FlixBus-eu", "route_short_name": "NULL", "route_long_name": "Riga - Warsaw - Vienna", "agency_url": "https://global.flixbus.com", "duration_min": "660", "duration_avg": "660", "duration_count": "4"}, {"agency_name": "FlixBus-eu", "route_short_name": "NULL", "route_long_name": "Warsaw - Budapest -  Bucharest", "agency_url": "https://global.flixbus.com", "duration_min": "535", "duration_avg": "535", "duration_count": "9"}, {"agency_name": "FlixBus-eu", "route_short_name": "NULL", "route_long_name": "Warsaw - Zagreb/Baska", "agency_url": "https://global.flixbus.com", "duration_min": "540", "duration_avg": "540", "duration_count": "4"}]}, {"place_id": "slovakia_2", "place_name": "Kosice", "place_lat": "48.722918", "place_lon": "21.268721", "duration_min": "530", "details": [{"agency_name": "FlixBus-eu", "route_short_name": "NULL", "route_long_name": "Warsaw - Krakow - Budapest/Zagreb", "agency_url": "https://global.flixbus.com", "duration_min": "530", "duration_avg": "530", "duration_count": "20"}, {"agency_name": "FlixBus-eu", "route_short_name": "NULL", "route_long_name": "Warsaw - Poprad - Budapest/Dubrovnik", "agency_url": "https://global.flixbus.com", "duration_min": "560", "duration_avg": "560", "duration_count": "24"}, {"agency_name": "FlixBus-eu", "route_short_name": "NULL", "route_long_name": "Warszawa - Krak\u251c\u2502w - Kosice", "agency_url": "https://global.flixbus.com", "duration_min": "575", "duration_avg": "575", "duration_count": "19"}]}, {"place_id": "slovakia_3", "place_name": "Banska Bystrica", "place_lat": "48.734658", "place_lon": "19.163006", "duration_min": "510", "details": [{"agency_name": "FlixBus-eu", "route_short_name": "NULL", "route_long_name": "Warszawa - Krak\u251c\u2502w - Budapest", "agency_url": "https://global.flixbus.com", "duration_min": "510", "duration_avg": "510", "duration_count": "19"}]}, {"place_id": "slovakia_4", "place_name": "Zilina", "place_lat": "49.227043", "place_lon": "18.746006", "duration_min": "510", "details": [{"agency_name": "FlixBus-eu", "route_short_name": "NULL", "route_long_name": "Riga - Warsaw - Vienna", "agency_url": "https://global.flixbus.com", "duration_min": "510", "duration_avg": "510", "duration_count": "4"}]}, {"place_id": "switzerland_6", "place_name": "Zurich", "place_lat": "47.378968", "place_lon": "8.540534", "duration_min": "1225", "details": [{"agency_name": "FlixBus-eu", "route_short_name": "NULL", "route_long_name": "Warsaw - Munich - Zurich", "agency_url": "https://global.flixbus.com", "duration_min": "1225", "duration_avg": "1225", "duration_count": "17"}, {"agency_name": "FlixBus-de", "route_short_name": "NULL", "route_long_name": "Warsaw - Munich - Zurich", "agency_url": "https://www.delfi.de", "duration_min": "1225", "duration_avg": "1225", "duration_count": "2"}]}]}