{"place_id": "switzerland_6", "place_name": "Zurich", "place_lat": "47.378968", "place_lon": "8.540534", "place_brief_desc": "The largest city in Switzerland is a vibrant metropolis that combines urban flair with natural beauty.", "place_longer_desc": "The largest city in Switzerland is a vibrant metropolis that combines urban flair with natural beauty. Shopping is a must for some and Bahnhofstrasse is one of Europe's most expensive streets.", "place_image": "./static/images/zurich.png", "place_tags": "history", "place_links": "./static/cards/zurich.html", "place_country": "Switzerland", "hops": [{"place_id": "austria_4", "place_name": "Innsbruck", "place_lat": "47.263331", "place_lon": "11.400506", "duration_min": "230", "duration_max": "250", "duration_median": "247", "duration_count": "2"}, {"place_id": "austria_5", "place_name": "Bregenz", "place_lat": "47.503001", "place_lon": "9.739623", "duration_min": "120", "duration_max": "120", "duration_median": "120", "duration_count": "2"}, {"place_id": "belgium_1", "place_name": "Brussels", "place_lat": "50.835375", "place_lon": "4.335695", "duration_min": "545", "duration_max": "670", "duration_median": "621", "duration_count": "4"}, {"place_id": "belgium_4", "place_name": "Antwerp", "place_lat": "51.215807", "place_lon": "4.421165", "duration_min": "600", "duration_max": "725", "duration_median": "679", "duration_count": "4"}, {"place_id": "belgium_7", "place_name": "Namur", "place_lat": "50.468983", "place_lon": "4.862499", "duration_min": "500", "duration_max": "500", "duration_median": "500", "duration_count": "1"}, {"place_id": "croatia_1", "place_name": "Zagreb", "place_lat": "45.807411", "place_lon": "15.990291", "duration_min": "761", "duration_max": "761", "duration_median": "761", "duration_count": "1"}, {"place_id": "czechia_1", "place_name": "Prague", "place_lat": "50.081926", "place_lon": "14.451481", "duration_min": "565", "duration_max": "670", "duration_median": "629", "duration_count": "6"}, {"place_id": "france_105", "place_name": "Marseille", "place_lat": "43.3030300", "place_lon": "5.38055500", "duration_min": "640", "duration_max": "640", "duration_median": "640", "duration_count": "1"}, {"place_id": "france_125", "place_name": "Nimes", "place_lat": "43.8323870", "place_lon": "4.36608100", "duration_min": "705", "duration_max": "705", "duration_median": "705", "duration_count": "1"}, {"place_id": "france_162", "place_name": "Strasbourg", "place_lat": "48.585339", "place_lon": "7.734067", "duration_min": "205", "duration_max": "260", "duration_median": "230", "duration_count": "14"}, {"place_id": "france_19", "place_name": "Paris", "place_lat": "48.8404960", "place_lon": "2.36707900", "duration_min": "244", "duration_max": "580", "duration_median": "476", "duration_count": "6"}, {"place_id": "france_38", "place_name": "Toulouse", "place_lat": "43.6114370", "place_lon": "1.45423700", "duration_min": "950", "duration_max": "950", "duration_median": "950", "duration_count": "1"}, {"place_id": "france_85", "place_name": "Hendaye", "place_lat": "43.3531650", "place_lon": "-1.7820950", "duration_min": "1204", "duration_max": "1204", "duration_median": "1204", "duration_count": "1"}, {"place_id": "france_93", "place_name": "Lyon", "place_lat": "45.7605960", "place_lon": "4.85940900", "duration_min": "395", "duration_max": "435", "duration_median": "405", "duration_count": "5"}, {"place_id": "Germany_2", "place_name": "Dresden", "place_lat": "51.040221", "place_lon": "13.731409", "duration_min": "675", "duration_max": "690", "duration_median": "682", "duration_count": "4"}, {"place_id": "Germany_3", "place_name": "Nuremberg", "place_lat": "49.450748", "place_lon": "11.077955", "duration_min": "340", "duration_max": "460", "duration_median": "415", "duration_count": "8"}, {"place_id": "Germany_4", "place_name": "Munich", "place_lat": "48.140364", "place_lon": "11.558744", "duration_min": "230", "duration_max": "310", "duration_median": "278", "duration_count": "14"}, {"place_id": "Germany_6", "place_name": "Freiburg", "place_lat": "47.997974", "place_lon": "7.841344", "duration_min": "120", "duration_max": "180", "duration_median": "146", "duration_count": "23"}, {"place_id": "Germany_7", "place_name": "Hamburg", "place_lat": "53.55711", "place_lon": "9.997434", "duration_min": "765", "duration_max": "870", "duration_median": "828", "duration_count": "6"}, {"place_id": "Germany_8", "place_name": "Heidelberg", "place_lat": "49.403582", "place_lon": "8.67548", "duration_min": "264", "duration_max": "365", "duration_median": "321", "duration_count": "13"}, {"place_id": "italy_1", "place_name": "Venice", "place_lat": "45.444427", "place_lon": "12.315491", "duration_min": "500", "duration_max": "535", "duration_median": "511", "duration_count": "3"}, {"place_id": "italy_8", "place_name": "Turin", "place_lat": "45.067428", "place_lon": "7.672976", "duration_min": "390", "duration_max": "390", "duration_median": "390", "duration_count": "2"}, {"place_id": "netherlands_2", "place_name": "Rotterdam", "place_lat": "51.924804", "place_lon": "4.468771", "duration_min": "690", "duration_max": "690", "duration_median": "690", "duration_count": "1"}, {"place_id": "netherlands_8", "place_name": "Maastricht", "place_lat": "50.849811", "place_lon": "5.705876", "duration_min": "555", "duration_max": "555", "duration_median": "566", "duration_count": "1"}, {"place_id": "poland_2", "place_name": "Warsaw", "place_lat": "52.224729", "place_lon": "21.001417", "duration_min": "1210", "duration_max": "1210", "duration_median": "1210", "duration_count": "2"}, {"place_id": "poland_3", "place_name": "Wroclaw", "place_lat": "51.098075", "place_lon": "17.037084", "duration_min": "930", "duration_max": "930", "duration_median": "940", "duration_count": "2"}, {"place_id": "romania_3", "place_name": "Sibiu", "place_lat": "45.799977", "place_lon": "24.161575", "duration_min": "1365", "duration_max": "1365", "duration_median": "1365", "duration_count": "1"}, {"place_id": "slovakia_1", "place_name": "Bratislava", "place_lat": "48.154135", "place_lon": "17.097852", "duration_min": "690", "duration_max": "690", "duration_median": "708", "duration_count": "1"}, {"place_id": "slovenia_1", "place_name": "Ljubljana", "place_lat": "46.058687", "place_lon": "14.51294", "duration_min": "597", "duration_max": "597", "duration_median": "597", "duration_count": "1"}, {"place_id": "spain_44", "place_name": "San Sebastian", "place_lat": "43.317669", "place_lon": "-1.976704", "duration_min": "1235", "duration_max": "1235", "duration_median": "1238", "duration_count": "1"}, {"place_id": "switzerland_2", "place_name": "Bern", "place_lat": "46.948834", "place_lon": "7.439131", "duration_min": "90", "duration_max": "100", "duration_median": "95", "duration_count": "6"}, {"place_id": "switzerland_3", "place_name": "Geneva", "place_lat": "46.210209", "place_lon": "6.142455", "duration_min": "240", "duration_max": "290", "duration_median": "256", "duration_count": "6"}, {"place_id": "switzerland_4", "place_name": "Lucerne", "place_lat": "47.050179", "place_lon": "8.310186", "duration_min": "45", "duration_max": "70", "duration_median": "57", "duration_count": "7"}]}