{"place_id": "france_163", "place_name": "Arras", "place_lat": "50.286889", "place_lon": "2.781829", "place_brief_desc": "An unexpected gem of a city with an exceptional ensemble of Flemish-style arcaded buildings \u00e2\u20ac\u201c the main squares are especially lovely at night \u00e2\u20ac\u201c and two subterranean WWI sites. The city makes a good base for visits to the Battle of the Somme memorials.", "place_longer_desc": "./static/places/arras.html", "place_image": "./static/images/arras.png", "place_tags": "museums|history|kids| culture", "place_links": "https://www.lonelyplanet.com/search?q=avignon", "place_country": "France"}