{"place_id": "romania_1", "place_name": "Sighisoara", "place_lat": "46.226398", "place_lon": "24.795737", "place_brief_desc": "Sighi\u00c8\u2122oara is a UNESCO World Heritage Site and one of the best-preserved medieval towns in Europe. It is also the birthplace of Vlad the Impaler, the inspiration for Dracula. You can explore the colourful houses, the cobblestone streets, the clock tower, and the citadel that overlooks the town. You can also visit the house where Vlad was born, now a museum and a restaurant.", "place_longer_desc": "./static/places/sighisoara.html", "place_image": "./static/images/sighisoara.png", "place_tags": "history", "place_links": "https://www.lonelyplanet.com/search?q=Sighi\u00c8\u2122oara", "place_country": "Romania"}