[{"from_place_id": "france_152", "to_place_id": "france_106", "agency_name": "SNCF", "route_short_name": "NULL", "route_long_name": "Lyon Part Dieu - Avignon", "agency_url": "http://www.sncf.com", "duration_min": "17", "duration_median": "17", "duration_count": "12"}, {"from_place_id": "france_152", "to_place_id": "france_106", "agency_name": "SNCF", "route_short_name": "NULL", "route_long_name": "Marseille - Avignon Centre - Valence - Lyon", "agency_url": "http://www.sncf.com", "duration_min": "16", "duration_median": "18", "duration_count": "31"}, {"from_place_id": "france_152", "to_place_id": "france_106", "agency_name": "SNCF", "route_short_name": "NULL", "route_long_name": "Marseille - Miramas - Avignon Centre Via Arles", "agency_url": "http://www.sncf.com", "duration_min": "16", "duration_median": "21", "duration_count": "56"}, {"from_place_id": "france_152", "to_place_id": "france_106", "agency_name": "SNCF (Soci\u251c\u00aet\u251c\u00ae Nationale des Chemins de fer Fran\u251c\u00baais)", "route_short_name": "NULL", "route_long_name": "631D", "agency_url": "http://www.sbb.ch", "duration_min": "17", "duration_median": "17", "duration_count": "28"}, {"from_place_id": "france_152", "to_place_id": "france_106", "agency_name": "SNCF (Soci\u251c\u00aet\u251c\u00ae Nationale des Chemins de fer Fran\u251c\u00baais)", "route_short_name": "NULL", "route_long_name": "K4", "agency_url": "http://www.sbb.ch", "duration_min": "16", "duration_median": "17", "duration_count": "91"}, {"from_place_id": "france_152", "to_place_id": "france_106", "agency_name": "SNCF (Soci\u251c\u00aet\u251c\u00ae Nationale des Chemins de fer Fran\u251c\u00baais)", "route_short_name": "NULL", "route_long_name": "TER 17701", "agency_url": "http://www.sbb.ch", "duration_min": "17", "duration_median": "18", "duration_count": "6"}, {"from_place_id": "france_152", "to_place_id": "france_106", "agency_name": "SNCF (Soci\u251c\u00aet\u251c\u00ae Nationale des Chemins de fer Fran\u251c\u00baais)", "route_short_name": "NULL", "route_long_name": "TER 17703", "agency_url": "http://www.sbb.ch", "duration_min": "17", "duration_median": "17", "duration_count": "3"}, {"from_place_id": "france_152", "to_place_id": "france_106", "agency_name": "SNCF (Soci\u251c\u00aet\u251c\u00ae Nationale des Chemins de fer Fran\u251c\u00baais)", "route_short_name": "NULL", "route_long_name": "TER 17705", "agency_url": "http://www.sbb.ch", "duration_min": "17", "duration_median": "17", "duration_count": "3"}, {"from_place_id": "france_152", "to_place_id": "france_106", "agency_name": "SNCF (Soci\u251c\u00aet\u251c\u00ae Nationale des Chemins de fer Fran\u251c\u00baais)", "route_short_name": "NULL", "route_long_name": "TER 886553", "agency_url": "http://www.sbb.ch", "duration_min": "17", "duration_median": "17", "duration_count": "3"}, {"from_place_id": "france_152", "to_place_id": "france_106", "agency_name": "SNCF (Soci\u251c\u00aet\u251c\u00ae Nationale des Chemins de fer Fran\u251c\u00baais)", "route_short_name": "NULL", "route_long_name": "TER 886557", "agency_url": "http://www.sbb.ch", "duration_min": "16", "duration_median": "16", "duration_count": "3"}, {"from_place_id": "france_152", "to_place_id": "france_106", "agency_name": "SNCF (Soci\u251c\u00aet\u251c\u00ae Nationale des Chemins de fer Fran\u251c\u00baais)", "route_short_name": "NULL", "route_long_name": "TER 886561", "agency_url": "http://www.sbb.ch", "duration_min": "17", "duration_median": "17", "duration_count": "3"}, {"from_place_id": "france_152", "to_place_id": "france_106", "agency_name": "SNCF (Soci\u251c\u00aet\u251c\u00ae Nationale des Chemins de fer Fran\u251c\u00baais)", "route_short_name": "NULL", "route_long_name": "TER 886565", "agency_url": "http://www.sbb.ch", "duration_min": "27", "duration_median": "27", "duration_count": "2"}, {"from_place_id": "france_152", "to_place_id": "france_106", "agency_name": "SNCF (Soci\u251c\u00aet\u251c\u00ae Nationale des Chemins de fer Fran\u251c\u00baais)", "route_short_name": "NULL", "route_long_name": "TER 886569", "agency_url": "http://www.sbb.ch", "duration_min": "17", "duration_median": "17", "duration_count": "3"}, {"from_place_id": "france_152", "to_place_id": "france_106", "agency_name": "SNCF (Soci\u251c\u00aet\u251c\u00ae Nationale des Chemins de fer Fran\u251c\u00baais)", "route_short_name": "NULL", "route_long_name": "TER 886573", "agency_url": "http://www.sbb.ch", "duration_min": "16", "duration_median": "16", "duration_count": "3"}, {"from_place_id": "france_152", "to_place_id": "france_106", "agency_name": "SNCF (Soci\u251c\u00aet\u251c\u00ae Nationale des Chemins de fer Fran\u251c\u00baais)", "route_short_name": "NULL", "route_long_name": "TER 886577", "agency_url": "http://www.sbb.ch", "duration_min": "17", "duration_median": "17", "duration_count": "6"}, {"from_place_id": "france_152", "to_place_id": "france_106", "agency_name": "SNCF (Soci\u251c\u00aet\u251c\u00ae Nationale des Chemins de fer Fran\u251c\u00baais)", "route_short_name": "NULL", "route_long_name": "TER 886581", "agency_url": "http://www.sbb.ch", "duration_min": "16", "duration_median": "16", "duration_count": "4"}, {"from_place_id": "france_152", "to_place_id": "france_106", "agency_name": "SNCF (Soci\u251c\u00aet\u251c\u00ae Nationale des Chemins de fer Fran\u251c\u00baais)", "route_short_name": "NULL", "route_long_name": "TGV 6191", "agency_url": "http://www.sbb.ch", "duration_min": "24", "duration_median": "24", "duration_count": "1"}, {"from_place_id": "france_152", "to_place_id": "france_106", "agency_name": "SNCF (Soci\u251c\u00aet\u251c\u00ae Nationale des Chemins de fer Fran\u251c\u00baais)", "route_short_name": "NULL", "route_long_name": "TGV 6193", "agency_url": "http://www.sbb.ch", "duration_min": "17", "duration_median": "17", "duration_count": "3"}, {"from_place_id": "france_152", "to_place_id": "france_106", "agency_name": "SNCF (Soci\u251c\u00aet\u251c\u00ae Nationale des Chemins de fer Fran\u251c\u00baais)", "route_short_name": "NULL", "route_long_name": "TGV 6195", "agency_url": "http://www.sbb.ch", "duration_min": "17", "duration_median": "17", "duration_count": "4"}, {"from_place_id": "france_152", "to_place_id": "france_106", "agency_name": "SNCF", "route_short_name": "NULL", "route_long_name": "Paris - Vall\u251c\u00aee du Rh\u251c\u2524ne TGV", "agency_url": "http://www.sncf.com", "duration_min": "17", "duration_median": "17", "duration_count": "17"}]