[{"from_place_id": "france_83", "to_place_id": "portugal_4", "agency_name": "FlixBus-eu", "route_short_name": "NULL", "route_long_name": "Porto - San Sebastian - Toulouse", "agency_url": "https://global.flixbus.com", "duration_min": "705", "duration_median": "705", "duration_count": "4"}, {"from_place_id": "france_83", "to_place_id": "portugal_4", "agency_name": "BlaBlaCar Bus", "route_short_name": "NULL", "route_long_name": "Paris - Bercy Seine > Porto - TIC Campanh\u251c\u00fa", "agency_url": "https://www.blablacar.co.uk/bus?comuto_cmkt=UK_GMAPS-PRO_ALL_ALL&utm_medium=Partnership&utm_source=Gmaps&utm_campaign=UK_GMAPS-PRO_ALL_ALL", "duration_min": "880", "duration_median": "880", "duration_count": "5"}]