[{"from_place_id": "Germany_9", "to_place_id": "france_153", "agency_name": "FlixBus-eu", "route_short_name": "NULL", "route_long_name": "London - Brussels - Cologne - Frankfurt", "agency_url": "https://global.flixbus.com", "duration_min": "390", "duration_median": "390", "duration_count": "16"}, {"from_place_id": "Germany_9", "to_place_id": "france_153", "agency_name": "FlixBus-de", "route_short_name": "NULL", "route_long_name": "London - Brussels - Cologne - Frankfurt", "agency_url": "https://www.delfi.de", "duration_min": "390", "duration_median": "390", "duration_count": "8"}]